{"docs_javascript_frame_uniapp_index.md":"af5ccb2c","docs_others_docker_index.md":"a2602b7f","docs_css_磨砂玻璃效果.md":"88ab729f","docs_javascript_books_index.md":"153a95a3","docs_java_index.md":"ab13441c","docs_javascript_books_javascript高级程序设计_07-迭代器与生成器.md":"aa057121","docs_others_index.md":"56a498d6","docs_javascript_books_javascript正则表达式迷你书_index.md":"6251e2fd","docs_javascript_books_javascript高级程序设计_01-javascript组成.md":"0f81bae8","docs_others_规范_前端规范_index.md":"501fdca5","docs_javascript_others_array查询元素索引执行效率差异.md":"49c8d86e","docs_others_规范_前端规范_通用命名规范.md":"496f591b","docs_javascript_frame_threejs_index.md":"7e69d826","docs_javascript_books_javascript高级程序设计_02-script标签.md":"9c3c9aef","docs_others_规范_前端规范_html规约.md":"22a81847","docs_javascript_others_index.md":"b9ef2ab1","index.md":"aeab93c1","docs_javascript_books_javascript高级程序设计_index.md":"09bd616b","docs_html_滑动标尺.md":"97915ae9","docs_javascript_index.md":"161898fe","docs_javascript_frame_微信小程序_index.md":"2cc24279","docs_javascript_frame_微前端_index.md":"825d81e8","docs_javascript_books_javascript高级程序设计_03-javascript语言基础.md":"2f155957","docs_rust_index.md":"f7ab8d5c","docs_others_规范_前端规范_css规约.md":"b1736fc5","docs_javascript_frame_微前端_qiankun_index.md":"339358ab","docs_others_规范_index.md":"b58ecdc3","docs_javascript_books_javascript高级程序设计_04-javascript变量、作用域与内存.md":"72bb9092","docs_javascript_frame_index.md":"8fc4df38","docs_javascript_others_for循环中return、break、continue作用.md":"a41dd92b","docs_javascript_books_javascript高级程序设计_08-对象、类与面向对象编程.md":"38dd39e0","docs_css_index.md":"f5e892df","docs_css_水波纹效果.md":"cb11a03e","docs_others_vpn_index.md":"8c56f88e","docs_others_vpn_v2ray.md":"e1b36a4a","docs_javascript_books_javascript高级程序设计_05-基础引用类型.md":"ac0ce9bb","docs_others_规范_前端规范_javascript规约.md":"4e2a9c65","docs_javascript_books_javascript高级程序设计_06-集合引用类型.md":"9001d8be","docs_others_规范_前端规范_vue规约.md":"6b965fd7","docs_javascript_webpack_index.md":"8007b992","docs_html_环形进度条（canvas）.md":"a55e1085","docs_html_index.md":"3881a016"}
